ecfeed.py
ecfeed_cli.py
ecfeed-2.1.3.dist-info/LICENSE
ecfeed-2.1.3.dist-info/METADATA
ecfeed-2.1.3.dist-info/WHEEL
ecfeed-2.1.3.dist-info/entry_points.txt
ecfeed-2.1.3.dist-info/top_level.txt
ecfeed-2.1.3.dist-info/RECORD
