Metadata-Version: 2.1
Name: ecfeed
Version: 2.1.3
Summary: Python interface for accessing EcFeed online generator service
Home-page: https://github.com/ecfeed/ecfeed.python
Author: EcFeed AS
Author-email: mail@ecfeed.com
Keywords: testing pairwise test_generation
Classifier: Development Status :: 4 - Beta
Classifier: Programming Language :: Python :: 3
Classifier: License :: OSI Approved :: MIT License
Classifier: Operating System :: OS Independent
Classifier: Environment :: Console
Classifier: Topic :: Software Development :: Libraries :: Python Modules
Classifier: Topic :: Software Development :: Testing
Classifier: Programming Language :: Python :: 3
Requires-Python: >=3.6
License-File: LICENSE
Requires-Dist: pyopenssl
Requires-Dist: requests
